README.md
setup.py
calor_pared_compuesta_lineal/ParedCompuesta.py
calor_pared_compuesta_lineal/__init__.py
calor_pared_compuesta_lineal.egg-info/PKG-INFO
calor_pared_compuesta_lineal.egg-info/SOURCES.txt
calor_pared_compuesta_lineal.egg-info/dependency_links.txt
calor_pared_compuesta_lineal.egg-info/requires.txt
calor_pared_compuesta_lineal.egg-info/top_level.txt