Metadata-Version: 2.1
Name: calor-pared-compuesta-lineal
Version: 0.0.1
Summary: Esta es la descripcion de mi paquete
Home-page: https://github.com/Valarg0502/calor_pared_compuesta_lineal
Download-URL: https://github.com/Valarg0502/calor_pared_compuesta_lineal/tarball/0.0.1
Author: Valentina Argüellez Angulo
Author-email: valentina.arguellez@gmail.com
License: MIT
Keywords: transferencia de calor,pared compuesta,termodinamica
